ctypes_rgb_values/LICENSE
ctypes_rgb_values/README.MD
ctypes_rgb_values/__init__.py
ctypes_rgb_values/requirements.txt
ctypes_rgb_values/thirdparty.json
ctypes_rgb_values-0.11.dist-info/LICENSE.rst
ctypes_rgb_values-0.11.dist-info/METADATA
ctypes_rgb_values-0.11.dist-info/WHEEL
ctypes_rgb_values-0.11.dist-info/top_level.txt
ctypes_rgb_values-0.11.dist-info/RECORD
