Metadata-Version: 2.1
Name: ctypes-rgb-values
Version: 0.11
Summary: Get rgb values at mouse position
Home-page: https://github.com/hansalemaos/ctypes_rgb_values
Author: Johannes Fischer
Author-email: aulasparticularesdealemaosp@gmail.com
License: MIT
Keywords: ctypes,windows,rgb,screenshot
Classifier: Development Status :: 4 - Beta
Classifier: Programming Language :: Python :: 3 :: Only
Classifier: Programming Language :: Python :: 3.10
Classifier: Topic :: Software Development :: Libraries :: Python Modules
Classifier: Topic :: Utilities
License-File: LICENSE.rst
Requires-Dist: ansi
